{
  "relative_filename": "config/components/positioned/goblin_ear_left.json",
  "version": "1.0.0",
  "author": "config/author.json",
  "component_id": "goblin_ear_left",
  "hardware_reference": "config/components/hardware/speaker.json",
  "interface_assignment": "I2S_DEVICE_2",
  "coordinate_system": "skull_3d",
  "reference_point": "nose_center",
  "position": {
    "x": "-2.5 INCH",
    "y": "+1.2 INCH",
    "z": "+0.5 INCH"
  },
  "orientation": {
    "tilt": "45 DEGREES",
    "rotation": "-30 DEGREES",
    "roll": "0 DEGREES"
  },
  "function": "audio_input_left"
}
