{
    "relative_filename":  "config/hardware/hw506_temperature_sensor.json",
    "version":  "1.0.0",
    "author":  "config/author.json",
    "component_type":  "TEMPERATURE_SENSOR",
    "hardware_name":  "HW-506 Temperature Sensor Module",
    "description":  "HW-506 analog temperature sensor module with LM35 or similar sensor",
    "created":  "2025-10-23",
    "hardware_specs":  {
                           "sensor_type":  "analog_temperature",
                           "temperature_range":  "-55C_to_150C",
                           "accuracy":  "?1C_typical",
                           "output_scale":  "10mV_per_degree_C",
                           "linearity":  "?0.4C_max_deviation"
                       },
    "physical_properties":  {
                                "board_dimensions":  {
                                                         "width":  "24mm",
                                                         "length":  "15mm",
                                                         "height":  "8mm"
                                                     },
                                "weight":  "2g",
                                "mounting_holes":  {
                                                       "count":  2,
                                                       "diameter":  "2.5mm",
                                                       "spacing":  "18mm"
                                                   }
                            },
    "control_interface":  {
                              "protocol":  "analog",
                              "output_type":  "analog_voltage",
                              "output_range":  "0V_to_1.5V_typical",
                              "adc_resolution":  "12_bit_recommended",
                              "reference_voltage":  "3.3V"
                          },
    "power_requirements":  {
                               "operating_voltage":  "2.7V-5.5V",
                               "typical_voltage":  "3.3V",
                               "current_consumption":  "60uA_typical",
                               "max_current":  "10mA"
                           },
    "pin_mapping":  {
                        "pins":  [
                                     {
                                         "pin_name":  "VCC",
                                         "direction":  "input",
                                         "description":  "Power supply positive",
                                         "electrical_type":  "power"
                                     },
                                     {
                                         "pin_name":  "GND",
                                         "direction":  "input",
                                         "description":  "Ground reference",
                                         "electrical_type":  "ground"
                                     },
                                     {
                                         "pin_name":  "OUT",
                                         "direction":  "output",
                                         "description":  "Analog voltage output proportional to temperature",
                                         "electrical_type":  "analog_output"
                                     }
                                 ]
                    },
    "software":  {
                     "init_function":  "hw506_temperature_sensor_init",
                     "act_function":  "hw506_temperature_sensor_act",
                     "libraries_required":  [

                                            ],
                     "sample_code_pattern":  "adc_analog_reading"
                 },
    "component_behavior":  {
                               "poll_interval_ms":  1000,
                               "adc_samples":  8,
                               "temperature_smoothing":  "5_sample_rolling_average",
                               "calibration_offset":  "adjustable_in_software"
                           },
    "calibration":  {
                        "zero_point":  "0C_equals_0mV",
                        "scale_factor":  "10mV_per_degree_C",
                        "reference_points":  [
                                                 {
                                                     "temp_c":  0,
                                                     "voltage_mv":  0
                                                 },
                                                 {
                                                     "temp_c":  25,
                                                     "voltage_mv":  250
                                                 },
                                                 {
                                                     "temp_c":  100,
                                                     "voltage_mv":  1000
                                                 }
                                             ]
                    },
    "name":  "hw506_temperature_sensor"
}
